spacy_udpipe/__init__.py
spacy_udpipe/languages.json
spacy_udpipe/tokenizer.py
spacy_udpipe/udpipe.py
spacy_udpipe/utils.py
spacy_udpipe-1.0.0.dist-info/LICENSE
spacy_udpipe-1.0.0.dist-info/METADATA
spacy_udpipe-1.0.0.dist-info/WHEEL
spacy_udpipe-1.0.0.dist-info/entry_points.txt
spacy_udpipe-1.0.0.dist-info/top_level.txt
spacy_udpipe-1.0.0.dist-info/RECORD
