Metadata-Version: 2.1
Name: spacy-udpipe
Version: 1.0.0
Summary: Use fast UDPipe models directly in spaCy
Home-page: https://github.com/TakeLab/spacy-udpipe
Author: TakeLab
Author-email: takelab@fer.hr
License: MIT
Project-URL: SpaCy, https://spacy.io/
Project-URL: TakeLab, http://takelab.fer.hr/
Project-URL: UDPipe, http://ufal.mff.cuni.cz/udpipe
Project-URL: Source, https://github.com/TakeLab/spacy-udpipe
Project-URL: Tracker, https://github.com/TakeLab/spacy-udpipe/issues
Keywords: nlp udpipe spacy python
Platform: UNKNOWN
Classifier: Development Status :: 4 - Beta
Classifier: Intended Audience :: Developers
Classifier: Programming Language :: Python :: 3
Classifier: License :: OSI Approved :: MIT License
Classifier: Operating System :: OS Independent
Requires-Python: >=3.6
Requires-Dist: spacy (<4.0.0,>=3.0.0)
Requires-Dist: ufal.udpipe (>=1.2.0)
